{
  "format_version": "1.0",
  "export_timestamp": "2025-08-30T04:17:37",
  "curves": [
    {
      "id": 0,
      "type": "bezier",
      "degree": 3,
      "control_points": [
        [
          49.78248596191406,
          53.94374084472656
        ],
        [
          47.423194885253906,
          42.13998031616211
        ],
        [
          60.176883697509766,
          49.305992126464844
        ],
        [
          47.8913459777832,
          49.94541931152344
        ]
      ],
      "metadata": {
        "name": "demo_curve_0",
        "generator_type": "quantum_vqc_demo",
        "length": 0.0,
        "bounding_box": {
          "min": [
            47.423194885253906,
            42.13998031616211
          ],
          "max": [
            60.176883697509766,
            53.94374084472656
          ]
        }
      }
    },
    {
      "id": 1,
      "type": "bezier",
      "degree": 3,
      "control_points": [
        [
          48.00575256347656,
          51.8050537109375
        ],
        [
          48.65631866455078,
          40.98192596435547
        ],
        [
          61.24681854248047,
          48.00128173828125
        ],
        [
          48.399169921875,
          51.5838737487793
        ]
      ],
      "metadata": {
        "name": "demo_curve_1",
        "generator_type": "quantum_vqc_demo",
        "length": 0.0,
        "bounding_box": {
          "min": [
            48.00575256347656,
            40.98192596435547
          ],
          "max": [
            61.24681854248047,
            51.8050537109375
          ]
        }
      }
    },
    {
      "id": 2,
      "type": "bezier",
      "degree": 3,
      "control_points": [
        [
          50.5882682800293,
          55.45212173461914
        ],
        [
          48.615238189697266,
          43.77356719970703
        ],
        [
          56.6558952331543,
          51.299293518066406
        ],
        [
          48.37403869628906,
          49.04996871948242
        ]
      ],
      "metadata": {
        "name": "demo_curve_2",
        "generator_type": "quantum_vqc_demo",
        "length": 0.0,
        "bounding_box": {
          "min": [
            48.37403869628906,
            43.77356719970703
          ],
          "max": [
            56.6558952331543,
            55.45212173461914
          ]
        }
      }
    },
    {
      "id": 3,
      "type": "bezier",
      "degree": 3,
      "control_points": [
        [
          53.95713424682617,
          54.28206253051758
        ],
        [
          54.5781364440918,
          48.84091567993164
        ],
        [
          49.58888244628906,
          50.9415283203125
        ],
        [
          44.011444091796875,
          51.254974365234375
        ]
      ],
      "metadata": {
        "name": "demo_curve_3",
        "generator_type": "quantum_vqc_demo",
        "length": 0.0,
        "bounding_box": {
          "min": [
            44.011444091796875,
            48.84091567993164
          ],
          "max": [
            54.5781364440918,
            54.28206253051758
          ]
        }
      }
    },
    {
      "id": 4,
      "type": "bezier",
      "degree": 3,
      "control_points": [
        [
          49.385990142822266,
          53.744632720947266
        ],
        [
          50.2990608215332,
          42.132484436035156
        ],
        [
          57.112648010253906,
          50.70682144165039
        ],
        [
          48.40732192993164,
          51.055179595947266
        ]
      ],
      "metadata": {
        "name": "demo_curve_4",
        "generator_type": "quantum_vqc_demo",
        "length": 0.0,
        "bounding_box": {
          "min": [
            48.40732192993164,
            42.132484436035156
          ],
          "max": [
            57.112648010253906,
            53.744632720947266
          ]
        }
      }
    }
  ]
}